<?xml version="1.0" encoding="UTF-8"?>
<logitrack>
 <configuracion>
 <centros>
 <centro id="C001">
 <nombre>Centro Norte</nombre>
 <ciudad>Guatemala City</ciudad>
 <capacidad>300</capacidad>
 </centro>
 <centro id="C002">
 <nombre>Centro Occidente</nombre>
 <ciudad>Quetzaltenango</ciudad>
 <capacidad>200</capacidad>
 </centro>
 <centro id="C001">
 <nombre>centro sur identico a otro</nombre>
 <ciudad>Guatemala City</ciudad>
 <capacidad>100</capacidad>
 </centro>
 <centro id="C004">
 <nombre>centro sin capacidad</nombre>
 <ciudad>Izabal</ciudad>
 <capacidad>0</capacidad>
 </centro>
 <centro id="C004">
 <nombre>centro con capacidad y con id distinto</nombre>
 <ciudad>amatitlan</ciudad>
 <capacidad>15</capacidad>
 </centro>
 <centro id="C005">
<nombre>centro con capacidad y con id distinto</nombre>
<ciudad>amatitlan</ciudad>
<capacidad>15</capacidad>
</centro>
<centro id="C006">
<nombre>centro con capacidad y con id distinto</nombre>
<ciudad>amatitlan</ciudad>
<capacidad>15</capacidad>
</centro>
<centro id="C007">
<nombre>centro con capacidad y con id distinto</nombre>
<ciudad>amatitlan</ciudad>
<capacidad>15</capacidad>
</centro>
<centro id="C008">
<nombre>centro con capacidad y con id distinto</nombre>
<ciudad>amatitlan</ciudad>
<capacidad>15</capacidad>
</centro>
<centro id="C009">
<nombre>centro con capacidad y con id distinto</nombre>
<ciudad>amatitlan</ciudad>
<capacidad>15</capacidad>
</centro>
<centro id="C010">
<nombre>centro con capacidad y con id distinto</nombre>
<ciudad>amatitlan</ciudad>
<capacidad>15</capacidad>
</centro>
<centro id="C014">
<nombre>centro con capacidad y con id distinto</nombre>
<ciudad>amatitlan</ciudad>
<capacidad>15</capacidad>
</centro>
<centro id="C016">
<nombre>centro con capacidad y con id distinto</nombre>
<ciudad>amatitlan</ciudad>
<capacidad>15</capacidad>
</centro>
 </centros>
 <rutas>
 <ruta id="R001" origen="C001" destino="C002" distancia="205"/>
 <ruta id="R002" origen="C002" destino="C001" distancia="210"/>
 <ruta id="R002" origen="mismo id" destino="C004" distancia="234"/>
 <ruta id="mismo origen destino que otro" origen="C002" destino="C001" distancia="234"/>
 <ruta id="mismo origen destino" origen="C002" destino="C002" distancia="234"/>
 <ruta id="nuevas rutas" origen="C004" destino="C001" distancia="210"/>
 <ruta id="R003" origen="C005" destino="C001" distancia="210"/>
 </rutas>
 <mensajeros>
 <mensajero id="M001" nombre="Carlos Méndez" capacidad="10" centro="C001"/>
 <mensajero id="M002" nombre="Ana López" capacidad="10" centro="C002"/>
 </mensajeros>
 <paquetes>
 <paquete id="P001" cliente="Empresa X" peso="15" destino="C002" estado="PENDIENTE" centroActual="C001"/>
 <paquete id="P002" cliente="Empresa y" peso="20" destino="C002" estado="PENDIENTE" centroActual="C001"/>
 <paquete id="P003" cliente="Empresa z" peso="20" destino="C003" estado="PENDIENTE" centroActual="C002"/>
 <paquete id="P004" cliente="Empresa w" peso="23" destino="C004" estado="PENDIENTE" centroActual="C004"/>
 </paquetes>
 <solicitudes>
 <solicitud id="S001" tipo="EnvioNormal" paquete="P001" prioridad="7"/>
 </solicitudes>
 </configuracion>
</logitrack>